setup.cfg
setup.py
yld/__init__.py
yld/__main__.py
yld/git.py
yld/tag.py
yld.egg-info/PKG-INFO
yld.egg-info/SOURCES.txt
yld.egg-info/dependency_links.txt
yld.egg-info/entry_points.txt
yld.egg-info/requires.txt
yld.egg-info/top_level.txt