Metadata-Version: 1.0
Name: yld
Version: 0.2.0
Summary: Deployment helper
Home-page: https://github.com/ewilazarus/yld
Author: Gabriel Lima
Author-email: gvclima@gmail.com
License: MIT
Keywords: deployment
Platform: UNKNOWN
